MANIFEST.in
README.rst
pyproject.toml
requirements.core.txt
requirements.txt
setup.py
core_module_auto_key_integer_sequence_app/__init__.py
core_module_auto_key_integer_sequence_app/urls.py
core_module_auto_key_integer_sequence_app/views.py
core_module_auto_key_integer_sequence_app.egg-info/PKG-INFO
core_module_auto_key_integer_sequence_app.egg-info/SOURCES.txt
core_module_auto_key_integer_sequence_app.egg-info/dependency_links.txt
core_module_auto_key_integer_sequence_app.egg-info/requires.txt
core_module_auto_key_integer_sequence_app.egg-info/top_level.txt
tests/__init__.py
tests/test_settings.py