Metadata-Version: 1.0
Name: core-module-auto-key-integer-sequence-app
Version: 1.20.0
Summary: Auto key (sequence of integers) module for the parser core project
Home-page: https://github.com/usnistgov/core_module_auto_key_integer_sequence_app
Author: NIST IT Lab
Author-email: itl_inquiries@nist.gov
License: UNKNOWN
Platform: UNKNOWN
